{
  "@type" : "sc:AnnotationList",
  "resources" : [ {
    "resource" : [ {
      "http://dev.llgc.org.uk/sas/full_text" : "VSOP (Very Special Old Pale) is a cognac is a cognac whose youngest brandy has aged at least &nbsp;for five years in an oak barrel.",
      "@type" : "dctypes:Text",
      "format" : "text/html",
      "chars" : "<p><strong>VSOP</strong> (Very Special Old Pale) is a cognac is a cognac whose youngest brandy has aged at least &nbsp;for five years in an oak barrel.</p>"
    } ],
    "@type" : "oa:Annotation",
    "dcterms:creator" : "https://dev.gdmrdigital.com/user/1240244679/111618135605349851906",
    "motivation" : [ "oa:commenting" ],
    "dcterms:created" : "2023-01-06T14:08:25",
    "@id" : "https://dev.gdmrdigital.com/annotation/anno/1673014105473",
    "dcterms:modified" : "2023-01-06T14:08:25",
    "@context" : "file:/usr/local/tomcat/webapps/ROOT/contexts/iiif-2.0.json",
    "on" : [ {
      "within" : {
        "@type" : "sc:Manifest",
        "@id" : "https://Clem0312.github.io/MartellCognac/manifests/manifest2.json"
      },
      "@type" : "oa:SpecificResource",
      "selector" : {
        "default" : {
          "@type" : "oa:FragmentSelector",
          "value" : "xywh=428,396,193,85"
        },
        "item" : {
          "@type" : "oa:SvgSelector",
          "value" : "<svg xmlns='http://www.w3.org/2000/svg'><path xmlns=\"http://www.w3.org/2000/svg\" d=\"M427.70639,395.92746h96.33679v0h96.33679v42.45078v42.45078h-96.33679h-96.33679v-42.45078z\" data-paper-data=\"{&quot;strokeWidth&quot;:1,&quot;rotation&quot;:0,&quot;deleteIcon&quot;:null,&quot;rotationIcon&quot;:null,&quot;group&quot;:null,&quot;editable&quot;:true,&quot;annotation&quot;:null}\" id=\"rectangle_689989e8-344d-41d3-8e3c-02faa72d786a\" fill-opacity=\"0\" fill=\"#00bfff\" fill-rule=\"nonzero\" stroke=\"#00bfff\" stroke-width=\"1\" stroke-linecap=\"butt\" stroke-linejoin=\"miter\" stroke-miterlimit=\"10\" stroke-dasharray=\"\" stroke-dashoffset=\"0\" font-family=\"none\" font-weight=\"none\" font-size=\"none\" text-anchor=\"none\" style=\"mix-blend-mode: normal\"/></svg>"
        },
        "@type" : "oa:Choice"
      },
      "full" : "http://9b04c4fe-d165-48a7-8065-b549e3bf9135"
    } ]
  } ],
  "@id" : "https://Clem0312.github.io/MartellCognac/annotations/72710e1cc6cdeacdb8042bb7252b306d.json",
  "@context" : "http://iiif.io/api/presentation/2/context.json"
}